torchneuromorphic/__init__.py
torchneuromorphic/combined_dataset.py
torchneuromorphic/events_timeslices.py
torchneuromorphic/neuromorphic_dataset.py
torchneuromorphic/template_hdf5.py
torchneuromorphic/transforms.py
torchneuromorphic/utils.py
torchneuromorphic/EMGGestures/__init__.py
torchneuromorphic/EMGGestures/emg_gestures.py
torchneuromorphic/aedat_generic/__init__.py
torchneuromorphic/aedat_generic/create_hdf5.py
torchneuromorphic/aedat_generic/dvsgestures_dataloaders.py
torchneuromorphic/double_dvssign/__init__.py
torchneuromorphic/double_dvssign/doubledvssign_dataloaders.py
torchneuromorphic/double_dvssign/test_doubledvssign.py
torchneuromorphic/doublenmnist/__init__.py
torchneuromorphic/doublenmnist/doublenmnist_dataloaders.py
torchneuromorphic/doublenmnist_torchmeta/__init__.py
torchneuromorphic/doublenmnist_torchmeta/doublenmnist_dataloaders.py
torchneuromorphic/dvs_gestures/__init__.py
torchneuromorphic/dvs_gestures/create_hdf5.py
torchneuromorphic/dvs_gestures/dvsgestures_dataloaders.py
torchneuromorphic/dvssign/__init__.py
torchneuromorphic/dvssign/create_dvssign.py
torchneuromorphic/dvssign/create_hdf5_sign.py
torchneuromorphic/dvssign/dvssign_dataloaders.py
torchneuromorphic/dvssign/test_dvssign.py
torchneuromorphic/nmnist/__init__.py
torchneuromorphic/nmnist/create_hdf5.py
torchneuromorphic/nmnist/create_nmnist_small.py
torchneuromorphic/nmnist/create_nmnist_small_noxtgt.py
torchneuromorphic/nmnist/nmnist_dataloaders.py
torchneuromorphic/ntidigits/__init__.py
torchneuromorphic/ntidigits/ntidigits_dataloaders.py
torchneuromorphic/rosbags/__init__.py
torchneuromorphic/rosbags/create_hdf5.py
torchneuromorphic/rosbags/rosbags_dataloaders.py
torchneuromorphic/shd/__init__.py
torchneuromorphic/shd/shd_dataloaders.py
torchneuromorphic/ssc/__init__.py
torchneuromorphic/ssc/ssc_dataloaders.py
torchneuromorphic-0.3.6.dist-info/LICENSE
torchneuromorphic-0.3.6.dist-info/METADATA
torchneuromorphic-0.3.6.dist-info/WHEEL
torchneuromorphic-0.3.6.dist-info/top_level.txt
torchneuromorphic-0.3.6.dist-info/RECORD
