Metadata-Version: 2.1
Name: torchneuromorphic
Version: 0.3.6
Summary: Dataset loaders for pytorch
Home-page: UNKNOWN
Author: Emre Neftci
Author-email: eneftci@uci.edu
License: Apache License 2.0
Download-URL: https://github.com/nmi-lab/torchneuromorphic/archive/0.3.1.tar.gz
Platform: UNKNOWN
Requires-Dist: dv
Requires-Dist: h5py
Requires-Dist: pandas
Requires-Dist: scipy (>=1.0)
Requires-Dist: torch (>=1.1.0)
Requires-Dist: torchvision (>=0.4.1)
